flask_postgresql_wrapper.py
tests/__init__.py
tests/flask_postgresql_wrapper_test.py
flask_postgresql_wrapper-1.0.1.dist-info/LICENSE
flask_postgresql_wrapper-1.0.1.dist-info/METADATA
flask_postgresql_wrapper-1.0.1.dist-info/WHEEL
flask_postgresql_wrapper-1.0.1.dist-info/top_level.txt
flask_postgresql_wrapper-1.0.1.dist-info/RECORD
