Metadata-Version: 2.1
Name: flask-postgresql-wrapper
Version: 1.0.1
Summary: Flask PostgreSQL Wrapper is a simple adapter for PostgreSQL with connection pooling.
Home-page: https://github.com/bernardocouto/flask-postgresql-wrapper
Author: Bernardo Couto
Author-email: bernardocouto.py@gmail.com
License: MIT
Keywords: flask postgresql
Platform: any
Classifier: License :: OSI Approved :: MIT License
Classifier: Operating System :: OS Independent
Classifier: Programming Language :: Python
Classifier: Programming Language :: Python :: 3
Classifier: Topic :: Database
License-File: LICENSE
Requires-Dist: dbutils
Requires-Dist: psycopg2-binary
Requires-Dist: pystache
